.gitignore
README.ipynb
README.md
README.py
dist.sh
pyproject.toml
README_files/README_2_0.png
README_files/README_3_0.png
README_files/README_4_0.png
README_files/README_5_0.png
README_files/README_6_0.png
README_files/README_7_0.png
dist/eyck-0.0.2-py3-none-any.whl
dist/eyck-0.0.2.dev1+g32d3f6b-py3-none-any.whl
dist/eyck-0.0.2.dev1+g32d3f6b.tar.gz
dist/eyck-0.0.2.tar.gz
dist/genomeplot-0.0.1-py3-none-any.whl
dist/genomeplot-0.0.1.tar.gz
scripts/heatmaps.py
scripts/render_readme.sh
src/polyptich/__init__.py
src/polyptich/colorbar.py
src/polyptich/paths.py
src/polyptich/utils.py
src/polyptich.egg-info/PKG-INFO
src/polyptich.egg-info/SOURCES.txt
src/polyptich.egg-info/dependency_links.txt
src/polyptich.egg-info/requires.txt
src/polyptich.egg-info/top_level.txt
src/polyptich/grid/__init__.py
src/polyptich/grid/broken.py
src/polyptich/grid/element.py
src/polyptich/grid/figure.py
src/polyptich/grid/grid.py
src/polyptich/grid/panel.py
src/polyptich/heatmap/__init__.py
src/polyptich/heatmap/annotation.py
src/polyptich/heatmap/heading.py
src/polyptich/heatmap/heatmap.py
src/polyptich/heatmap/layouts.py
src/polyptich/heatmap/ticks.py
src/polyptich/render/__init__.py
src/polyptich/render/convert.py