Metadata-Version: 2.2
Name: polyptich
Version: 0.0.16
Summary: Extra visualization functions
Author-email: Wouter Saelens <wouter.saelens@gmail.com>
License: MIT
Project-URL: Homepage, https://github.com/zouter/polyptich
Project-URL: Bug Tracker, https://github.com/zouter/polyptich/issues
Keywords: visualization
Classifier: Programming Language :: Python :: 3
Requires-Python: >=3.8
Requires-Dist: matplotlib
Requires-Dist: numpy
Provides-Extra: dev
Requires-Dist: pytest; extra == "dev"
Provides-Extra: test
Requires-Dist: pytest; extra == "test"
Requires-Dist: ruff; extra == "test"
